{
  "persona": {
    "id": "quiet-luxury-casual",
    "display_name": "Demo: Maya",
    "description": "A synthetic persona whose saved style is more structured and formal than her everyday purchases."
  },
  "aspiration": {
    "dimensions": {
      "color_boldness": 0.72,
      "formality": 0.81,
      "price_tier": 0.76,
      "silhouette_structure": 0.84
    },
    "evidence_ids": ["pin-01", "pin-02", "pin-03", "pin-04"]
  },
  "behavior": {
    "dimensions": {
      "color_boldness": 0.44,
      "formality": 0.39,
      "price_tier": 0.47,
      "silhouette_structure": 0.36
    },
    "evidence_ids": ["purchase-01", "purchase-02", "purchase-03", "survey-01"],
    "typical_spend_range": [25, 120],
    "regret_profile": {
      "color_boldness": 0.68,
      "formality": 0.75,
      "price_tier": 0.82,
      "silhouette_structure": 0.79
    }
  },
  "evidence": [
    {
      "id": "pin-01",
      "source": "pinterest_fixture",
      "label": "Tailored camel blazer",
      "kind": "aspirational"
    },
    {
      "id": "pin-02",
      "source": "pinterest_fixture",
      "label": "Structured woven tote",
      "kind": "aspirational"
    },
    {
      "id": "pin-03",
      "source": "pinterest_fixture",
      "label": "Minimal gold jewelry",
      "kind": "aspirational"
    },
    {
      "id": "pin-04",
      "source": "pinterest_fixture",
      "label": "Wide-leg tailored trousers",
      "kind": "aspirational"
    },
    {
      "id": "purchase-01",
      "source": "gmail_fixture",
      "label": "Everyday cotton hoodie",
      "kind": "purchase"
    },
    {
      "id": "purchase-02",
      "source": "gmail_fixture",
      "label": "Running sneakers",
      "kind": "purchase"
    },
    {
      "id": "purchase-03",
      "source": "gmail_fixture",
      "label": "Soft unstructured tote",
      "kind": "purchase"
    },
    {
      "id": "purchase-04",
      "source": "gmail_fixture",
      "label": "Returned structured camel blazer",
      "kind": "purchase"
    },
    {
      "id": "survey-01",
      "source": "survey_fixture",
      "label": "Rarely wears a returned structured blazer",
      "kind": "survey"
    }
  ],
  "survey": [
    {
      "id": "purchase-check-in-01",
      "item_id": "purchase-01",
      "item_name": "Everyday cotton hoodie",
      "merchant": "Everlane",
      "price": 68,
      "currency": "USD",
      "purchased_at": "2026-05-18",
      "returned": false,
      "comment_prompt": "Anything else about how this hoodie fits into your life?",
      "prompts": [
        {
          "id": "hoodie-feeling",
          "key": "emotional_feedback",
          "question": "How do you feel about it now?",
          "options": ["Love it", "Neutral", "Regret it"]
        },
        {
          "id": "hoodie-frequency",
          "key": "usage_frequency",
          "question": "How often do you wear or use it?",
          "options": ["Often", "Sometimes", "Rarely", "Never"]
        },
        {
          "id": "hoodie-motivation",
          "key": "purchase_motivation",
          "question": "What drove the purchase?",
          "options": ["Needed it", "Matched my taste", "On sale", "Impulse or influence"]
        }
      ]
    },
    {
      "id": "purchase-check-in-02",
      "item_id": "purchase-04",
      "item_name": "Structured camel blazer",
      "merchant": "Studio Archive",
      "price": 189,
      "currency": "USD",
      "purchased_at": "2026-06-04",
      "returned": true,
      "comment_prompt": "Anything else you want us to understand about this return?",
      "prompts": [
        {
          "id": "blazer-return-reason",
          "key": "return_reason",
          "question": "Why did you return it?",
          "options": ["Fit or comfort", "Quality", "Looked different", "Price or value", "Changed my mind"]
        },
        {
          "id": "blazer-return-sentiment",
          "key": "return_sentiment",
          "question": "How did returning it feel?",
          "options": ["Relieved", "Neutral", "Still wanted it", "Regret returning it"]
        },
        {
          "id": "blazer-motivation",
          "key": "purchase_motivation",
          "question": "What drove the purchase?",
          "options": ["Needed it", "Matched my taste", "On sale", "Impulse or influence"]
        }
      ]
    }
  ],
  "candidate": {
    "name": "Structured saffron shoulder bag",
    "price": 145,
    "dimensions": {
      "color_boldness": 0.78,
      "formality": 0.72,
      "price_tier": 0.73,
      "silhouette_structure": 0.86
    }
  }
}
